{
    "key": "group_6706dc7a882c2",
    "title": "Logo Grid",
    "fields": [
        {
            "key": "field_6706e03fec783",
            "label": "Título",
            "name": "titulo",
            "aria-label": "",
            "type": "text",
            "instructions": "",
            "required": 0,
            "conditional_logic": 0,
            "wrapper": {
                "width": "60",
                "class": "",
                "id": ""
            },
            "default_value": "Título",
            "maxlength": "",
            "allow_in_bindings": 0,
            "placeholder": "",
            "prepend": "",
            "append": ""
        },
        {
            "key": "field_6706e04eec784",
            "label": "Subtítulo",
            "name": "subtitulo",
            "aria-label": "",
            "type": "text",
            "instructions": "",
            "required": 0,
            "conditional_logic": 0,
            "wrapper": {
                "width": "40",
                "class": "",
                "id": ""
            },
            "default_value": "Subtítulo",
            "maxlength": "",
            "allow_in_bindings": 0,
            "placeholder": "",
            "prepend": "",
            "append": ""
        },
        {
            "key": "field_6706dc7a8ec22",
            "label": "Logos",
            "name": "logos",
            "aria-label": "",
            "type": "repeater",
            "instructions": "",
            "required": 0,
            "conditional_logic": 0,
            "wrapper": {
                "width": "",
                "class": "",
                "id": ""
            },
            "layout": "table",
            "pagination": 0,
            "min": 0,
            "max": 0,
            "collapsed": "",
            "button_label": "Add Row",
            "rows_per_page": 20,
            "sub_fields": [
                {
                    "key": "field_6706dd408ec23",
                    "label": "Logo",
                    "name": "logo",
                    "aria-label": "",
                    "type": "image",
                    "instructions": "",
                    "required": 0,
                    "conditional_logic": 0,
                    "wrapper": {
                        "width": "",
                        "class": "",
                        "id": ""
                    },
                    "return_format": "",
                    "library": "",
                    "min_width": "",
                    "min_height": "",
                    "min_size": "",
                    "max_width": "",
                    "max_height": "",
                    "max_size": "",
                    "mime_types": "",
                    "allow_in_bindings": 0,
                    "preview_size": "medium",
                    "parent_repeater": "field_6706dc7a8ec22"
                }
            ]
        }
    ],
    "location": [
        [
            {
                "param": "block",
                "operator": "==",
                "value": "acf\/logo-grid"
            }
        ]
    ],
    "menu_order": 0,
    "position": "normal",
    "style": "default",
    "label_placement": "top",
    "instruction_placement": "label",
    "hide_on_screen": "",
    "active": true,
    "description": "",
    "show_in_rest": 0,
    "modified": 1728504010
}
